faster_hexbytes__mypyc.cpython-314t-darwin.so
faster_hexbytes/__init__.py
faster_hexbytes/_utils.cpython-314t-darwin.so
faster_hexbytes/main.cpython-314t-darwin.so
faster_hexbytes/__init__.cpython-314t-darwin.so
faster_hexbytes/py.typed
faster_hexbytes/main.py
faster_hexbytes/_utils.py
faster_hexbytes-1.3.6.dist-info/RECORD
faster_hexbytes-1.3.6.dist-info/WHEEL
faster_hexbytes-1.3.6.dist-info/top_level.txt
faster_hexbytes-1.3.6.dist-info/METADATA
faster_hexbytes-1.3.6.dist-info/licenses/LICENSE
