Metadata-Version: 2.4
Name: faster_hexbytes
Version: 1.3.6
Summary: A faster fork of hexbytes: Python `bytes` subclass that decodes hex, with a readable console output. Implemented in C.
Home-page: https://github.com/BobTheBuidler/faster-hexbytes
Author: The Ethereum Foundation
Author-email: snakecharmers@ethereum.org
License: MIT
Project-URL: Documentation, https://hexbytes.readthedocs.io/en/stable/
Project-URL: Release Notes, https://github.com/BobTheBuidler/faster-hexbytes/releases
Project-URL: Issues, https://github.com/BobTheBuidler/faster-hexbytes/issues
Project-URL: Source - Precompiled (.py), https://github.com/BobTheBuidler/faster-hexbytes/tree/master/faster_eth_utils
Project-URL: Source - Compiled (.c), https://github.com/BobTheBuidler/faster-hexbytes/tree/master/build
Project-URL: Benchmarks, https://github.com/BobTheBuidler/faster-hexbytes/tree/master/benchmarks
Project-URL: Benchmarks - Results, https://github.com/BobTheBuidler/faster-hexbytes/tree/master/benchmarks/results
Project-URL: Original, https://github.com/ethereum/hexbytes
Keywords: ethereum
Classifier: Development Status :: 5 - Production/Stable
Classifier: Intended Audience :: Developers
Classifier: License :: OSI Approved :: MIT License
Classifier: Natural Language :: English
Classifier: Programming Language :: Python :: 3
Classifier: Programming Language :: Python :: 3.9
Classifier: Programming Language :: Python :: 3.10
Classifier: Programming Language :: Python :: 3.11
Classifier: Programming Language :: Python :: 3.12
Classifier: Programming Language :: Python :: 3.13
Classifier: Programming Language :: Python :: 3.14
Requires-Python: >=3.9, <4
License-File: LICENSE
Requires-Dist: hexbytes==1.3.1
Requires-Dist: mypy_extensions<2,>=0.4.2
Requires-Dist: typing-extensions<5,>=4.0.0
Provides-Extra: dev
Requires-Dist: build>=0.9.0; extra == "dev"
Requires-Dist: bump_my_version>=0.19.0; extra == "dev"
Requires-Dist: ipython; extra == "dev"
Requires-Dist: mypy==1.19.1; extra == "dev"
Requires-Dist: pre-commit>=3.4.0; extra == "dev"
Requires-Dist: tox>=4.0.0; extra == "dev"
Requires-Dist: twine; extra == "dev"
Requires-Dist: wheel; extra == "dev"
Requires-Dist: sphinx>=6.0.0; extra == "dev"
Requires-Dist: sphinx-autobuild>=2021.3.14; extra == "dev"
Requires-Dist: sphinx_rtd_theme>=1.0.0; extra == "dev"
Requires-Dist: towncrier<26,>=25; extra == "dev"
Requires-Dist: eth_utils>=2.0.0; extra == "dev"
Requires-Dist: hypothesis>=3.44.24; extra == "dev"
Requires-Dist: pytest>=7.0.0; extra == "dev"
Requires-Dist: pytest-xdist>=2.4.0; extra == "dev"
Provides-Extra: docs
Requires-Dist: sphinx>=6.0.0; extra == "docs"
Requires-Dist: sphinx-autobuild>=2021.3.14; extra == "docs"
Requires-Dist: sphinx_rtd_theme>=1.0.0; extra == "docs"
Requires-Dist: towncrier<26,>=25; extra == "docs"
Provides-Extra: test
Requires-Dist: eth_utils>=2.0.0; extra == "test"
Requires-Dist: hypothesis>=3.44.24; extra == "test"
Requires-Dist: pytest>=7.0.0; extra == "test"
Requires-Dist: pytest-xdist>=2.4.0; extra == "test"
Provides-Extra: benchmark
Requires-Dist: pytest-benchmark; extra == "benchmark"
Requires-Dist: pytest-codspeed<4.3,>=4.2; extra == "benchmark"
Requires-Dist: eth-typing; extra == "benchmark"
Provides-Extra: codspeed
Requires-Dist: pytest-codspeed<4.3,>=4.2; extra == "codspeed"
Requires-Dist: eth-typing; extra == "codspeed"
Dynamic: author
Dynamic: author-email
Dynamic: classifier
Dynamic: description
Dynamic: description-content-type
Dynamic: home-page
Dynamic: keywords
Dynamic: license
Dynamic: license-file
Dynamic: project-url
Dynamic: provides-extra
Dynamic: requires-dist
Dynamic: requires-python
Dynamic: summary
